setup.py
ircmess/__init__.py
ircmess.egg-info/PKG-INFO
ircmess.egg-info/SOURCES.txt
ircmess.egg-info/dependency_links.txt
ircmess.egg-info/not-zip-safe
ircmess.egg-info/top_level.txt