Metadata-Version: 1.0
Name: ircmess
Version: 0.1
Summary: Simple and fast IRC line parser
Home-page: https://github.com/lyska/ircmess
Author: Sam Dodrill
Author-email: shadow.h511@gmail.com
License: Zlib
Platform: UNKNOWN
